bqskitrs-0.4.1.dist-info/METADATA
bqskitrs-0.4.1.dist-info/WHEEL
bqskitrs-0.4.1.dist-info/license_files/LICENSE
bqskitrs.libs/libquadmath-96973f99.so.0
bqskitrs.libs/libgfortran-040039e1.so.5
bqskitrs/__init__.py
bqskitrs/bqskitrs.abi3.so
bqskitrs-0.4.1.dist-info/RECORD
