Metadata-Version: 2.1
Name: bqskitrs
Version: 0.4.1
License-File: LICENSE
Author: Ethan Smith <ethanhs@lbl.gov>, Ed Younis <edyounis@lbl.gov>
Author-email: Ethan Smith <ethanhs@lbl.gov>, Ed Younis <edyounis@lbl.gov>
Maintainer-email: Ethan Smith <ethanhs@lbl.gov>, Ed Younis <edyounis@lbl.gov>
License: LGPL-2.1 AND BSD-3-Clause
Requires-Python: >=3.8
Project-URL: Source, https://github.com/bqskit/bqskitrs
